bash_kernel/__init__.py
bash_kernel/__main__.py
bash_kernel/display.py
bash_kernel/install.py
bash_kernel/kernel.py
bash_kernel/resources/__init__.py
bash_kernel/resources/logo-svg.svg
bash_kernel-0.9.2.dist-info/LICENSE
bash_kernel-0.9.2.dist-info/WHEEL
bash_kernel-0.9.2.dist-info/METADATA
bash_kernel-0.9.2.dist-info/RECORD
