Metadata-Version: 2.1
Name: bash_kernel
Version: 0.9.2
Summary: A bash kernel for Jupyter
Author-email: Thomas Kluyver <thomas@kluyver.me.uk>
Classifier: Framework :: Jupyter
Classifier: License :: OSI Approved :: BSD License
Classifier: Programming Language :: Python :: 3
Classifier: Topic :: System :: Shells
Requires-Dist: pexpect (>=4.0)
Requires-Dist: ipykernel
Project-URL: Source, https://github.com/takluyver/bash_kernel
